aiohttp_dashboard/__init__.py
aiohttp_dashboard/action.py
aiohttp_dashboard/core.py
aiohttp_dashboard/embedding.py
aiohttp_dashboard/endpoint.py
aiohttp_dashboard/event.py
aiohttp_dashboard/helper.py
aiohttp_dashboard/router.py
aiohttp_dashboard/static/index.html
aiohttp_dashboard/static/bundle/application.js
aiohttp_dashboard/static/bundle/bootstrap.css
aiohttp_dashboard/static/bundle/font-awesome/css/fa-brands.css
aiohttp_dashboard/static/bundle/font-awesome/css/fa-regular.css
aiohttp_dashboard/static/bundle/font-awesome/css/fa-solid.css
aiohttp_dashboard/static/bundle/font-awesome/css/fontawesome.css
aiohttp_dashboard/static/bundle/font-awesome/webfonts/fa-brands-400.eot
aiohttp_dashboard/static/bundle/font-awesome/webfonts/fa-brands-400.svg
aiohttp_dashboard/static/bundle/font-awesome/webfonts/fa-brands-400.ttf
aiohttp_dashboard/static/bundle/font-awesome/webfonts/fa-brands-400.woff
aiohttp_dashboard/static/bundle/font-awesome/webfonts/fa-brands-400.woff2
aiohttp_dashboard/static/bundle/font-awesome/webfonts/fa-regular-400.eot
aiohttp_dashboard/static/bundle/font-awesome/webfonts/fa-regular-400.svg
aiohttp_dashboard/static/bundle/font-awesome/webfonts/fa-regular-400.ttf
aiohttp_dashboard/static/bundle/font-awesome/webfonts/fa-regular-400.woff
aiohttp_dashboard/static/bundle/font-awesome/webfonts/fa-regular-400.woff2
aiohttp_dashboard/static/bundle/font-awesome/webfonts/fa-solid-900.eot
aiohttp_dashboard/static/bundle/font-awesome/webfonts/fa-solid-900.svg
aiohttp_dashboard/static/bundle/font-awesome/webfonts/fa-solid-900.ttf
aiohttp_dashboard/static/bundle/font-awesome/webfonts/fa-solid-900.woff
aiohttp_dashboard/static/bundle/font-awesome/webfonts/fa-solid-900.woff2
aiohttp_dashboard-0.0.3.dist-info/METADATA
aiohttp_dashboard-0.0.3.dist-info/WHEEL
aiohttp_dashboard-0.0.3.dist-info/top_level.txt
aiohttp_dashboard-0.0.3.dist-info/RECORD
